hagworm/__init__.py
hagworm/extend/__init__.py
hagworm/extend/base.py
hagworm/extend/cache.py
hagworm/extend/compile.py
hagworm/extend/config.py
hagworm/extend/crypto.py
hagworm/extend/error.py
hagworm/extend/event.py
hagworm/extend/igraph.py
hagworm/extend/interface.py
hagworm/extend/logging.py
hagworm/extend/media.py
hagworm/extend/metaclass.py
hagworm/extend/ntp.py
hagworm/extend/process.py
hagworm/extend/qrcode.py
hagworm/extend/struct.py
hagworm/extend/text.py
hagworm/extend/trace.py
hagworm/extend/transaction.py
hagworm/extend/validator.py
hagworm/extend/asyncio/__init__.py
hagworm/extend/asyncio/base.py
hagworm/extend/asyncio/buffer.py
hagworm/extend/asyncio/command.py
hagworm/extend/asyncio/event.py
hagworm/extend/asyncio/file.py
hagworm/extend/asyncio/future.py
hagworm/extend/asyncio/mail.py
hagworm/extend/asyncio/mongo.py
hagworm/extend/asyncio/mysql.py
hagworm/extend/asyncio/net.py
hagworm/extend/asyncio/pool.py
hagworm/extend/asyncio/redis.py
hagworm/extend/asyncio/socket.py
hagworm/extend/asyncio/task.py
hagworm/extend/asyncio/transaction.py
hagworm/frame/__init__.py
hagworm/frame/gunicorn.py
hagworm/frame/stress_tests.py
hagworm/frame/fastapi/__init__.py
hagworm/frame/fastapi/base.py
hagworm/frame/fastapi/field.py
hagworm/frame/fastapi/model.py
hagworm/frame/fastapi/response.py
hagworm/static/swagger-ui-bundle.js
hagworm/static/swagger-ui-bundle.js.map
hagworm/static/swagger-ui.css
hagworm/static/swagger-ui.css.map
hagworm/third/__init__.py
hagworm/third/grpc/__init__.py
hagworm/third/grpc/bridge.py
hagworm/third/grpc/client.py
hagworm/third/grpc/server.py
hagworm/third/nacos/__init__.py
hagworm/third/nacos/client.py
hagworm/third/nacos/config.py
hagworm/third/rabbitmq/__init__.py
hagworm/third/rabbitmq/consume.py
hagworm/third/rabbitmq/publish.py
hagworm/third/rabbitmq/rpc.py
hagworm-5.10.5.dist-info/licenses/LICENSE
hagworm-5.10.5.dist-info/WHEEL
hagworm-5.10.5.dist-info/METADATA
hagworm-5.10.5.dist-info/RECORD
