Metadata-Version: 2.4
Name: hagworm
Version: 5.10.5
Summary: Network Development Suite
Author-email: "Shaobo.Wang" <wsb310@gmail.com>
Requires-Python: >=3.10
License-Expression: Apache-2.0
Classifier: Programming Language :: Python :: 3.10
Classifier: Operating System :: POSIX :: Linux
License-File: LICENSE
Requires-Dist: Cython==3.0.10
Requires-Dist: APScheduler==3.10.4
Requires-Dist: ahocorasick-rs==0.22.0
Requires-Dist: Pillow==10.4.0
Requires-Dist: PyJWT==2.8.0
Requires-Dist: PyYAML==6.0.1
Requires-Dist: SQLAlchemy==2.0.31
Requires-Dist: coredis==4.17.0
Requires-Dist: asyncmy==0.2.9
Requires-Dist: aiosmtplib==3.0.1
Requires-Dist: aio-pika==9.4.2
Requires-Dist: cachetools==5.3.3
Requires-Dist: confluent-kafka==2.5.0
Requires-Dist: cryptography==42.0.8
Requires-Dist: elasticsearch==8.12.1
Requires-Dist: fastapi==0.111.1
Requires-Dist: filelock==3.15.4
Requires-Dist: gunicorn==22.0.0
Requires-Dist: grpcio==1.60.0
Requires-Dist: httpx==0.27.0
Requires-Dist: httptools==0.6.1
Requires-Dist: igraph==0.11.6
Requires-Dist: loguru==0.7.2
Requires-Dist: motor==3.5.1
Requires-Dist: msgpack==1.0.8
Requires-Dist: ntplib==0.4.0
Requires-Dist: psutil==6.0.0
Requires-Dist: pandas==2.2.2
Requires-Dist: pytest-asyncio==0.23.7
Requires-Dist: python-dateutil==2.8.2
Requires-Dist: python-stdnum==1.20
Requires-Dist: python-multipart==0.0.9
Requires-Dist: pymongo==4.8.0
Requires-Dist: qrcode==7.4.2
Requires-Dist: texttable==1.7.0
Requires-Dist: ujson==5.10.0
Requires-Dist: uvicorn[standard]==0.30.1
Requires-Dist: uvicorn-worker==0.2.0
Requires-Dist: uvloop==0.19.0;sys_platform!='win32'
Requires-Dist: xmltodict==0.13.0
